Workbook

Sheet Dashboard
A1: Enterprise Projects & Workforce Dashboard - Sample Data
A3: Metric | B3: Value | C3: Formula/Meaning | D3: Department | E3: Projects | F3: Employees
A4: Departments | B4: =COUNTA(Departments!A2:A100) -> 14 | C4: Active departments | D4: Executive Office | E4: =COUNTIF(Projects!D:D,D4) -> 3 | F4: =COUNTIF(Employees!E:E,D4) -> 6
A5: Employees | B5: =COUNTA(Employees!A2:A500) -> 124 | C5: Employee records | D5: Human Resources | E5: =COUNTIF(Projects!D:D,D5) -> 0 | F5: =COUNTIF(Employees!E:E,D5) -> 6
A6: Projects | B6: =COUNTA(Projects!A2:A200) -> 24 | C6: Project portfolio | D6: Finance | E6: =COUNTIF(Projects!D:D,D6) -> 2 | F6: =COUNTIF(Employees!E:E,D6) -> 6
A7: Open Tasks | B7: =COUNTIF(Tasks!I2:I1000,"<>Completed") -> 948 | C7: Tasks not completed | D7: Information Technology | E7: =COUNTIF(Projects!D:D,D7) -> 1 | F7: =COUNTIF(Employees!E:E,D7) -> 12
A8: Blocked Tasks | B8: =COUNTIF(Tasks!I2:I1000,"Blocked") -> 17 | C8: Current blockers | D8: Cybersecurity | E8: =COUNTIF(Projects!D:D,D8) -> 1 | F8: =COUNTIF(Employees!E:E,D8) -> 6
A9: At Risk Projects | B9: =COUNTIF(Projects!G2:G200,"At Risk") -> 6 | C9: Portfolio risk | D9: Digital Products | E9: =COUNTIF(Projects!D:D,D9) -> 1 | F9: =COUNTIF(Employees!E:E,D9) -> 9
A10: Meetings | B10: =COUNTA(Meetings!A2:A500) -> 180 | C10: Meeting records | D10: Data & Analytics | E10: =COUNTIF(Projects!D:D,D10) -> 1 | F10: =COUNTIF(Employees!E:E,D10) -> 7
A11: Activity Events | B11: =COUNTA('Activity Log'!A2:A1000) -> 700 | C11: System/activity log | D11: Marketing | E11: =COUNTIF(Projects!D:D,D11) -> 2 | F11: =COUNTIF(Employees!E:E,D11) -> 6
D12: Sales | E12: =COUNTIF(Projects!D:D,D12) -> 5 | F12: =COUNTIF(Employees!E:E,D12) -> 16
D13: Customer Experience | E13: =COUNTIF(Projects!D:D,D13) -> 0 | F13: =COUNTIF(Employees!E:E,D13) -> 14
A14: Project Status | B14: Count | D14: Operations | E14: =COUNTIF(Projects!D:D,D14) -> 2 | F14: =COUNTIF(Employees!E:E,D14) -> 18
A15: Not Started | B15: =COUNTIF(Projects!G:G,A15) -> 1 | D15: Procurement | E15: =COUNTIF(Projects!D:D,D15) -> 1 | F15: =COUNTIF(Employees!E:E,D15) -> 6
A16: Planning | B16: =COUNTIF(Projects!G:G,A16) -> 3 | D16: Legal & Compliance | E16: =COUNTIF(Projects!D:D,D16) -> 2 | F16: =COUNTIF(Employees!E:E,D16) -> 6
A17: In Progress | B17: =COUNTIF(Projects!G:G,A17) -> 7 | D17: Corporate Training | E17: =COUNTIF(Projects!D:D,D17) -> 3 | F17: =COUNTIF(Employees!E:E,D17) -> 6
A18: At Risk | B18: =COUNTIF(Projects!G:G,A18) -> 6
A19: On Hold | B19: =COUNTIF(Projects!G:G,A19) -> 2
A20: Completed | B20: =COUNTIF(Projects!G:G,A20) -> 5
A23: Weekly Health | B23: Count
A24: Green | B24: =COUNTIF('Weekly Updates'!F:F,A24) -> 199
A25: Amber | B25: =COUNTIF('Weekly Updates'!F:F,A25) -> 127
A26: Red | B26: =COUNTIF('Weekly Updates'!F:F,A26) -> 41

Sheet Departments
A1: Department ID | B1: Department Name | C1: Division | D1: Location | E1: Cost Center | F1: Director | G1: Headcount | H1: Annual Budget SAR
A2: D001 | B2: Executive Office | C2: Corporate | D2: Jeddah HQ | E2: Strategy & Governance | F2: Sara Alharbi | G2: 28 | H2: 8500000
A3: D002 | B3: Human Resources | C3: Corporate | D3: Riyadh Office | E3: People Operations | F3: Lina Alotaibi | G3: 44 | H3: 6200000
A4: D003 | B4: Finance | C4: Corporate | D4: Jeddah HQ | E4: Finance & Risk | F4: Fahad Alghamdi | G4: 52 | H4: 11200000
A5: D004 | B5: Information Technology | C5: Technology | D5: Jeddah HQ | E5: IT Operations | F5: Omar Alzahrani | G5: 96 | H5: 18900000
A6: D005 | B6: Cybersecurity | C6: Technology | D6: Riyadh Office | E6: Security & Compliance | F6: Maha Alshehri | G6: 38 | H6: 9700000
A7: D006 | B7: Digital Products | C7: Technology | D7: Jeddah HQ | E7: Product & Innovation | F7: Noura Alqahtani | G7: 74 | H7: 15400000
A8: D007 | B8: Data & Analytics | C8: Technology | D8: Remote | E8: Data Office | F8: Yousef Almutairi | G8: 61 | H8: 13200000
A9: D008 | B9: Marketing | C9: Commercial | D9: Dubai Office | E9: Brand & Growth | F9: Reem Alsubaie | G9: 49 | H9: 8200000
A10: D009 | B10: Sales | C10: Commercial | D10: Riyadh Office | E10: Revenue | F10: Abdullah Alrashid | G10: 132 | H10: 22100000
A11: D010 | B11: Customer Experience | C11: Operations | D11: Jeddah HQ | E11: Service Delivery | F11: Hanan Albalawi | G11: 118 | H11: 14600000
A12: D011 | B12: Operations | C12: Operations | D12: Dammam Office | E12: Field Operations | F12: Turki Alenezi | G12: 156 | H12: 24700000
A13: D012 | B13: Procurement | C13: Operations | D13: Riyadh Office | E13: Supply Management | F13: Abeer Aljohani | G13: 34 | H13: 7300000
... A15: D014 | B15: Corporate Training | C15: Corporate | D15: Remote | E15: Learning & Enablement | F15: Mona Alshammari | G15: 31 | H15: 4100000

Sheet Employees
A1: Employee ID | B1: Employee Name | C1: Email | D1: Department ID | E1: Department | F1: Job Title | G1: Level | H1: Manager | I1: Location | J1: Hire Date | K1: Employment Status
A2: E1030 | B2: Fatimah Alzahrani | C2: fatimah.alzahrani@example-company.com | D2: D004 | E2: Information Technology | F2: Administrator | G2: Administrator | H2: Department PMO | I2: Jeddah HQ | J2: 43183 | K2: Active
A3: E1002 | B3: Renad Almalki | C3: renad.almalki@example-company.com | D3: D001 | E3: Executive Office | F3: Product Manager | G3: Senior Specialist | H3: Department PMO | I3: Jeddah HQ | J3: 43119 | K3: Active
A4: E1003 | B4: Abeer Alharbi | C4: abeer.alharbi@example-company.com | D4: D001 | E4: Executive Office | F4: Support Engineer | G4: Associate | H4: Sara Alharbi | I4: Jeddah HQ | J4: 44968 | K4: Active
A5: E1004 | B5: Reem Alrashid | C5: reem.alrashid@example-company.com | D5: D001 | E5: Executive Office | F5: Business Analyst | G5: Senior Specialist | H5: Sara Alharbi | I5: Jeddah HQ | J5: 44467 | K5: Active
A6: E1005 | B6: Yousef Almutairi | C6: yousef.almutairi@example-company.com | D6: D001 | E6: Executive Office | F6: Sales Executive | G6: Associate | H6: Sara Alharbi | I6: Jeddah HQ | J6: 44206 | K6: Active
A7: E1006 | B7: Salwa Alrashid | C7: salwa.alrashid@example-company.com | D7: D001 | E7: Executive Office | F7: Project Manager | G7: Senior Specialist | H7: Department PMO | I7: Jeddah HQ | J7: 44286 | K7: Active
A8: E1007 | B8: Nasser Aljohani | C8: nasser.aljohani@example-company.com | D8: D002 | E8: Human Resources | F8: Finance Analyst | G8: Senior Specialist | H8: Lina Alotaibi | I8: Riyadh Office | J8: 43669 | K8: Active
A9: E1008 | B9: Fahad Alsubaie | C9: fahad.alsubaie@example-company.com | D9: D002 | E9: Human Resources | F9: Software Engineer | G9: Specialist | H9: Department PMO | I9: Riyadh Office | J9: 44230 | K9: Active
A10: E1009 | B10: Lina Almutairi | C10: lina.almutairi@example-company.com | D10: D002 | E10: Human Resources | F10: Cybersecurity Analyst | G10: Senior Specialist | H10: Lina Alotaibi | I10: Riyadh Office | J10: 43028 | K10: Active
A11: E1010 | B11: Khalid Almalki | C11: khalid.almalki@example-company.com | D11: D002 | E11: Human Resources | F11: HR Specialist | G11: Associate | H11: Lina Alotaibi | I11: Riyadh Office | J11: 45357 | K11: Active
A12: E1011 | B12: Turki Alenezi | C12: turki.alenezi@example-company.com | D12: D002 | E12: Human Resources | F12: Project Manager | G12: Associate | H12: Lina Alotaibi | I12: Riyadh Office | J12: 44028 | K12: Active
A13: E1012 | B13: Fahad Almutairi | C13: fahad.almutairi@example-company.com | D13: D002 | E13: Human Resources | F13: Sales Executive | G13: Associate | H13: Lina Alotaibi | I13: Riyadh Office | J13: 45369 | K13: Active
... A126: E1126 | B126: Bayan H | C126: bayan5152@gmail.com | D126: D014 | E126: Corporate Training | F126: Employee | G126: Employee | H126: Aishah | I126: Remote | J126: 46212 | K126: Active

Sheet Projects
A1: Project ID | B1: Project Name | C1: Department ID | D1: Department | E1: Owner ID | F1: Owner | G1: Status | H1: Priority | I1: Risk Level | J1: Start Date | K1: Target End Date | L1: Progress % | M1: Budget SAR | N1: Actual Spend SAR | O1: Strategic Theme
A2: P001 | B2: Enterprise Data Platform | C2: D001 | D2: Executive Office | E2: E1006 | F2: Salwa Alrashid | G2: In Progress | H2: Medium | I2: Medium | J2: 46165 | K2: 46328 | L2: 58 | M2: 1700000 | N2: 967396 | O2: Compliance
A3: P002 | B3: Customer Mobile App Revamp | C3: D009 | D3: Sales | E3: E1063 | F3: Nasser Almalki | G3: Completed | H3: Medium | I3: Low | J3: 46100 | K3: 46257 | L3: 100 | M3: 2050000 | N3: 1433944 | O3: Compliance
A4: P003 | B4: ERP Finance Automation | C4: D009 | D4: Sales | E4: E1059 | F4: Noura Aljohani | G4: Planning | H4: High | I4: Medium | J4: 46168 | K4: 46317 | L4: 8 | M4: 600000 | N4: 284268 | O4: Revenue Growth
A5: P004 | B5: Zero Trust Security Rollout | C5: D014 | D5: Corporate Training | E5: E1122 | F5: Noura Alenezi | G5: In Progress | H5: Low | I5: Low | J5: 46147 | K5: 46254 | L5: 49 | M5: 1750000 | N5: 1154508 | O5: Compliance
A6: P005 | B6: HR Self-Service Portal | C6: D013 | D6: Legal & Compliance | E6: E1116 | F6: Fahad Alotaibi | G6: In Progress | H6: Medium | I6: Medium | J6: 46114 | K6: 46288 | L6: 43 | M6: 2000000 | N6: 1698353 | O6: Revenue Growth
A7: P006 | B7: Sales CRM Migration | C7: D009 | D7: Sales | E7: E1074 | F7: Fatimah Alrashid | G7: In Progress | H7: Critical | I7: Low | J7: 46115 | K7: 46245 | L7: 54 | M7: 2350000 | N7: 655894 | O7: Digital Transformation
A8: P007 | B8: Vendor Risk Dashboard | C8: D006 | D8: Digital Products | E8: E1044 | F8: Fatimah Alharthi | G8: Completed | H8: High | I8: Low | J8: 46124 | K8: 46267 | L8: 100 | M8: 1750000 | N8: 1442026 | O8: Digital Transformation
A9: P008 | B9: AI Support Assistant | C9: D014 | D9: Corporate Training | E9: E1122 | F9: Noura Alenezi | G9: Completed | H9: Low | I9: Low | J9: 46052 | K9: 46231 | L9: 100 | M9: 2200000 | N9: 1820428 | O9: Revenue Growth
A10: P009 | B10: Digital Onboarding Journey | C10: D013 | D10: Legal & Compliance | E10: E1115 | F10: Abdullah Alshammari | G10: At Risk | H10: Critical | I10: High | J10: 46113 | K10: 46317 | L10: 64 | M10: 1150000 | N10: 799778 | O10: Employee Experience
A11: P010 | B11: Cloud Cost Optimization | C11: D001 | D11: Executive Office | E11: E1005 | F11: Yousef Almutairi | G11: At Risk | H11: Low | I11: Medium | J11: 46044 | K11: 46149 | L11: 35 | M11: 450000 | N11: 370058 | O11: Revenue Growth
A12: P011 | B12: Executive KPI Cockpit | C12: D003 | D12: Finance | E12: E1018 | F12: Reem Alharbi | G12: Not Started | H12: Medium | I12: Medium | J12: 46103 | K12: 46155 | L12: 0 | M12: 1500000 | N12: 313766 | O12: Operational Excellence
A13: P012 | B13: Operations Control Tower | C13: D003 | D13: Finance | E13: E1013 | F13: Saad Alshehri | G13: At Risk | H13: Low | I13: Medium | J13: 46124 | K13: 46327 | L13: 39 | M13: 1600000 | N13: 1129615 | O13: Revenue Growth
... A25: P024 | B25: Employee Engagement Analytics | C25: D011 | D25: Operations | E25: E1095 | F25: Turki Alghamdi | G25: On Hold | H25: Medium | I25: Medium | J25: 46032 | K25: 46089 | L25: 23 | M25: 350000 | N25: 252827 | O25: Operational Excellence

Sheet Tasks
A1: Task ID | B1: Project ID | C1: Project | D1: Task Name | E1: Assigned To ID | F1: Assigned To | G1: Department ID | H1: Department | I1: Status | J1: Priority | K1: Due Date | L1: Estimated Hours | M1: Actual Hours | N1: Completion %
A2: T0001 | B2: P001 | C2: Enterprise Data Platform | D2: Analyze user journey | E2: E1100 | F2: Raghad Alsubaie | G2: D011 | H2: Operations | I2: Backlog | J2: Medium | K2: 46318 | L2: 8 | N2: 22
A3: T0002 | B3: P001 | C3: Enterprise Data Platform | D3: Design dashboard layout | E3: E1015 | F3: Mohammed Alzahrani | G3: D003 | H3: Finance | I3: Backlog | J3: Medium | K3: 46199 | L3: 24 | N3: 33
A4: T0003 | B4: P001 | C4: Enterprise Data Platform | D4: Configure release plan | E4: E1007 | F4: Nasser Aljohani | G4: D002 | H4: Human Resources | I4: In Progress | J4: Low | K4: 46273 | L4: 40 | M4: 39 | N4: 75
A5: T0004 | B5: P001 | C5: Enterprise Data Platform | D5: Deploy vendor documents | E5: E1014 | F5: Razan Alomari | G5: D003 | H5: Finance | I5: Not Started | J5: Low | K5: 46294 | L5: 16 | N5: 3
A6: T0005 | B6: P001 | C6: Enterprise Data Platform | D6: Deploy API endpoints | E6: E1008 | F6: Fahad Alsubaie | G6: D002 | H6: Human Resources | I6: In Progress | J6: Low | K6: 46268 | L6: 40 | M6: 51 | N6: 10
A7: T0006 | B7: P001 | C7: Enterprise Data Platform | D7: Test stakeholder report | E7: E1042 | F7: Abdullah Alharthi | G7: D006 | H7: Digital Products | I7: Backlog | J7: High | K7: 46203 | L7: 24 | N7: 67
A8: T0007 | B8: P001 | C8: Enterprise Data Platform | D8: Migrate KPI definitions | E8: E1038 | F8: Fahad Alsubaie | G8: D006 | H8: Digital Products | I8: In Progress | J8: Low | K8: 46295 | L8: 6 | M8: 8 | N8: 98
A9: T0008 | B9: P001 | C9: Enterprise Data Platform | D9: Deploy automation workflow | E9: E1071 | F9: Mona Alsubaie | G9: D009 | H9: Sales | I9: In Progress | J9: Medium | K9: 46276 | L9: 32 | M9: 27 | N9: 53
A10: T0009 | B10: P001 | C10: Enterprise Data Platform | D10: Migrate KPI definitions | E10: E1094 | F10: Mona Alamri | G10: D011 | H10: Operations | I10: In Progress | J10: High | K10: 46246 | L10: 24 | M10: 37 | N10: 60
A11: T0010 | B11: P001 | C11: Enterprise Data Platform | D11: Approve dashboard layout | E11: E1009 | F11: Lina Almutairi | G11: D002 | H11: Human Resources | I11: Not Started | J11: Low | K11: 46187 | L11: 24 | N11: 71
A12: T0011 | B12: P001 | C12: Enterprise Data Platform | D12: Migrate training guide | E12: E1008 | F12: Fahad Alsubaie | G12: D002 | H12: Human Resources | I12: In Progress | J12: Low | K12: 46309 | L12: 32 | M12: 28 | N12: 54
A13: T0012 | B13: P001 | C13: Enterprise Data Platform | D13: Validate dashboard layout | E13: E1112 | F13: Abdullah Alrashid | G13: D012 | H13: Procurement | I13: In Progress | J13: High | K13: 46239 | L13: 6 | M13: 6 | N13: 84
A14: T0013 | B14: P001 | C14: Enterprise Data Platform | D14: Prepare security controls | E14: E1062 | F14: Renad Alzahrani | G14: D009 | H14: Sales | I14: In Progress | J14: High | K14: 46193 | L14: 6 | M14: 8 | N14: 54
A15: T0014 | B15: P002 | C15: Customer Mobile App Revamp | D15: Build user journey | E15: E1099 | F15: Raghad Alamri | G15: D011 | H15: Operations | I15: Backlog | J15: High | K15: 46243 | L15: 4 | N15: 89
A16: T0015 | B16: P002 | C16: Customer Mobile App Revamp | D16: Test API endpoints | E16: E1098 | F16: Abeer Almutairi | G16: D011 | H16: Operations | I16: In Progress | J16: Medium | K16: 46187 | L16: 8 | M16: 8 | N16: 18
A17: T0016 | B17: P002 | C17: Customer Mobile App Revamp | D17: Configure dashboard layout | E17: E1095 | F17: Turki Alghamdi | G17: D011 | H17: Operations | I17: In Review | J17: Medium | K17: 46124 | L17: 32 | M17: 30 | N17: 47
A18: T0017 | B18: P002 | C18: Customer Mobile App Revamp | D18: Prepare requirements | E18: E1040 | F18: Abdullah Alenezi | G18: D006 | H18: Digital Products | I18: In Progress | J18: Low | K18: 46246 | L18: 8 | M18: 5 | N18: 86
A19: T0018 | B19: P002 | C19: Customer Mobile App Revamp | D19: Validate training guide | E19: E1011 | F19: Turki Alenezi | G19: D002 | H19: Human Resources | I19: Blocked | J19: Critical | K19: 46214 | L19: 40 | M19: 38 | N19: 65
A20: T0019 | B20: P002 | C20: Customer Mobile App Revamp | D20: Design security controls | E20: E1015 | F20: Mohammed Alzahrani | G20: D003 | H20: Finance | I20: Not Started | J20: Critical | K20: 46211 | L20: 16 | N20: 50
A21: T0020 | B21: P002 | C21: Customer Mobile App Revamp | D21: Approve user journey | E21: E1077 | F21: Mohammed Almutairi | G21: D010 | H21: Customer Experience | I21: Not Started | J21: Medium | K21: 46102 | L21: 8 | N21: 37
A22: T0021 | B22: P002 | C22: Customer Mobile App Revamp | D22: Analyze access roles | E22: E1042 | F22: Abdullah Alharthi | G22: D006 | H22: Digital Products | I22: In Progress | J22: Critical | K22: 46102 | L22: 8 | M22: 5 | N22: 29
A23: T0022 | B23: P002 | C23: Customer Mobile App Revamp | D23: Design UAT scenarios | E23: E1065 | F23: Razan Alenezi | G23: D009 | H23: Sales | I23: Backlog | J23: Low | K23: 46191 | L23: 32 | N23: 9
A24: T0023 | B24: P002 | C24: Customer Mobile App Revamp | D24: Test requirements | E24: E1111 | F24: Noura Albalawi | G24: D012 | H24: Procurement | I24: In Progress | J24: Critical | K24: 46248 | L24: 32 | M24: 26 | N24: 41
A25: T0024 | B25: P002 | C25: Customer Mobile App Revamp | D25: Test stakeholder report | E25: E1022 | F25: Hanan Alghamdi | G25: D004 | H25: Information Technology | I25: Not Started | J25: Low | K25: 46193 | L25: 12 | N25: 51
A26: T0025 | B26: P002 | C26: Customer Mobile App Revamp | D26: Build API endpoints | E26: E1068 | F26: Hanan Alghamdi | G26: D009 | H26: Sales | I26: Completed | J26: High | K26: 46202 | L26: 12 | M26: 10 | N26: 100
A27: T0026 | B27: P002 | C27: Customer Mobile App Revamp | D27: Train vendor documents | E27: E1066 | F27: Hala Alqahtani | G27: D009 | H27: Sales | I27: In Progress | J27: High | K27: 46236 | L27: 24 | M27: 31 | N27: 18
A28: T0027 | B28: P002 | C28: Customer Mobile App Revamp | D28: Migrate API endpoints | E28: E1031 | F28: Abdullah Almalki | G28: D005 | H28: Cybersecurity | I28: In Progress | J28: Medium | K28: 46138 | L28: 8 | M28: 10 | N28: 22
A29: T0028 | B29: P002 | C29: Customer Mobile App Revamp | D29: Migrate data model | E29: E1122 | F29: Noura Alenezi | G29: D014 | H29: Corporate Training | I29: In Review | J29: Critical | K29: 46219 | L29: 24 | M29: 34 | N29: 19
A30: T0029 | B30: P002 | C30: Customer Mobile App Revamp | D30: Configure release plan | E30: E1057 | F30: Fatimah Alharthi | G30: D008 | H30: Marketing | I30: In Progress | J30: High | K30: 46221 | L30: 16 | M30: 18 | N30: 9
A31: T0030 | B31: P003 | C31: ERP Finance Automation | D31: Migrate database tables | E31: E1060 | F31: Razan Almutairi | G31: D009 | H31: Sales | I31: Backlog | J31: High | K31: 46178 | L31: 6 | N31: 11
A32: T0031 | B32: P003 | C32: ERP Finance Automation | D32: Prepare vendor documents | E32: E1079 | F32: Noura Almalki | G32: D010 | H32: Customer Experience | I32: In Progress | J32: Low | K32: 46267 | L32: 40 | M32: 59 | N32: 24
A33: T0032 | B33: P003 | C33: ERP Finance Automation | D33: Review training guide | E33: E1042 | F33: Abdullah Alharthi | G33: D006 | H33: Digital Products | I33: Not Started | J33: Low | K33: 46297 | L33: 40 | N33: 43
A34: T0033 | B34: P003 | C34: ERP Finance Automation | D34: Deploy release plan | E34: E1092 | F34: Sara Alharbi | G34: D011 | H34: Operations | I34: Blocked | J34: Low | K34: 46298 | L34: 12 | M34: 15 | N34: 66
A35: T0034 | B35: P003 | C35: ERP Finance Automation | D35: Configure vendor documents | E35: E1079 | F35: Noura Almalki | G35: D010 | H35: Customer Experience | I35: In Progress | J35: High | K35: 46262 | L35: 32 | M35: 30 | N35: 76
A36: T0035 | B36: P003 | C36: ERP Finance Automation | D36: Train vendor documents | E36: E1007 | F36: Nasser Aljohani | G36: D002 | H36: Human Resources | I36: In Progress | J36: Critical | K36: 46185 | L36: 16 | M36: 12 | N36: 77
A37: T0036 | B37: P003 | C37: ERP Finance Automation | D37: Document vendor documents | E37: E1112 | F37: Abdullah Alrashid | G37: D012 | H37: Procurement | I37: Not Started | J37: Medium | K37: 46254 | L37: 24 | N37: 89
A38: T0037 | B38: P003 | C38: ERP Finance Automation | D38: Migrate training guide | E38: E1085 | F38: Lina Alsubaie | G38: D010 | H38: Customer Experience | I38: In Progress | J38: Low | K38: 46202 | L38: 16 | M38: 17 | N38: 42
A39: T0038 | B39: P003 | C39: ERP Finance Automation | D39: Design data model | E39: E1105 | F39: Mona Alshehri | G39: D011 | H39: Operations | I39: Not Started | J39: Critical | K39: 46303 | L39: 24 | N39: 39
A40: T0039 | B40: P003 | C40: ERP Finance Automation | D40: Build dashboard layout | E40: E1024 | F40: Hala Almutairi | G40: D004 | H40: Information Technology | I40: Completed | J40: Critical | K40: 46256 | L40: 12 | M40: 8 | N40: 100
A41: T0040 | B41: P003 | C41: ERP Finance Automation | D41: Prepare dashboard layout | E41: E1010 | F41: Khalid Almalki | G41: D002 | H41: Human Resources | I41: In Progress | J41: Low | K41: 46194 | L41: 24 | M41: 35 | N41: 76
A42: T0041 | B42: P003 | C42: ERP Finance Automation | D42: Design automation workflow | E42: E1049 | F42: Omar Alghamdi | G42: D007 | H42: Data & Analytics | I42: Not Started | J42: Medium | K42: 46210 | L42: 40 | N42: 46
A43: T0042 | B43: P004 | C43: Zero Trust Security Rollout | D43: Document training guide | E43: E1093 | F43: Reem Alshehri | G43: D011 | H43: Operations | I43: In Progress | J43: Critical | K43: 46204 | L43: 12 | M43: 13 | N43: 100
A44: T0043 | B44: P004 | C44: Zero Trust Security Rollout | D44: Approve automation workflow | E44: E1061 | F44: Mona Almutairi | G44: D009 | H44: Sales | I44: In Progress | J44: Critical | K44: 46172 | L44: 40 | M44: 53 | N44: 64
A45: T0044 | B45: P004 | C45: Zero Trust Security Rollout | D45: Deploy database tables | E45: E1068 | F45: Hanan Alghamdi | G45: D009 | H45: Sales | I45: In Review | J45: Medium | K45: 46168 | L45: 16 | M45: 8 | N45: 47
A46: T0045 | B46: P004 | C46: Zero Trust Security Rollout | D46: Build user journey | E46: E1071 | F46: Mona Alsubaie | G46: D009 | H46: Sales | I46: Completed | J46: Low | K46: 46239 | L46: 16 | M46: 9 | N46: 100
A47: T0046 | B47: P004 | C47: Zero Trust Security Rollout | D47: Audit data model | E47: E1058 | F47: Omar Alrashid | G47: D008 | H47: Marketing | I47: Completed | J47: Low | K47: 46166 | L47: 12 | M47: 16 | N47: 100
A48: T0047 | B48: P004 | C48: Zero Trust Security Rollout | D48: Test API endpoints | E48: E1120 | F48: Ahmed Alrashid | G48: D014 | H48: Corporate Training | I48: Backlog | J48: High | K48: 46201 | L48: 12 | N48: 47
A49: T0048 | B49: P004 | C49: Zero Trust Security Rollout | D49: Document KPI definitions | E49: E1029 | F49: Renad Alshammari | G49: D004 | H49: Information Technology | I49: Completed | J49: High | K49: 46188 | L49: 8 | M49: 5 | N49: 100
A50: T0049 | B50: P004 | C50: Zero Trust Security Rollout | D50: Audit API endpoints | E50: E1107 | F50: Sara Alqahtani | G50: D012 | H50: Procurement | I50: Completed | J50: Critical | K50: 46237 | L50: 40 | M50: 47 | N50: 100
A51: T0050 | B51: P004 | C51: Zero Trust Security Rollout | D51: Validate user journey | E51: E1003 | F51: Abeer Alharbi | G51: D001 | H51: Executive Office | I51: Completed | J51: Critical | K51: 46175 | L51: 6 | M51: 8 | N51: 100
A52: T0051 | B52: P004 | C52: Zero Trust Security Rollout | D52: Audit UAT scenarios | E52: E1016 | F52: Maha Alomari | G52: D003 | H52: Finance | I52: In Progress | J52: Critical | K52: 46178 | L52: 6 | M52: 3 | N52: 76
A53: T0052 | B53: P004 | C53: Zero Trust Security Rollout | D53: Design stakeholder report | E53: E1069 | F53: Maha Alamri | G53: D009 | H53: Sales | I53: In Progress | J53: Medium | K53: 46228 | L53: 8 | M53: 6 | N53: 45
A54: T0053 | B54: P004 | C54: Zero Trust Security Rollout | D54: Review release plan | E54: E1031 | F54: Abdullah Almalki | G54: D005 | H54: Cybersecurity | I54: Not Started | J54: Low | K54: 46201 | L54: 24 | N54: 69
A55: T0054 | B55: P004 | C55: Zero Trust Security Rollout | D55: Test data model | E55: E1065 | F55: Razan Alenezi | G55: D009 | H55: Sales | I55: In Progress | J55: Critical | K55: 46212 | L55: 40 | M55: 21 | N55: 32
A56: T0055 | B56: P004 | C56: Zero Trust Security Rollout | D56: Migrate API endpoints | E56: E1096 | F56: Renad Alomari | G56: D011 | H56: Operations | I56: In Review | J56: High | K56: 46193 | L56: 12 | M56: 15 | N56: 98
A57: T0056 | B57: P004 | C57: Zero Trust Security Rollout | D57: Train vendor documents | E57: E1075 | F57: Turki Alrashid | G57: D010 | H57: Customer Experience | I57: In Progress | J57: Low | K57: 46244 | L57: 24 | M57: 26 | N57: 22
A58: T0057 | B58: P004 | C58: Zero Trust Security Rollout | D58: Review access roles | E58: E1107 | F58: Sara Alqahtani | G58: D012 | H58: Procurement | I58: In Progress | J58: Critical | K58: 46235 | L58: 8 | M58: 11 | N58: 99
A59: T0058 | B59: P004 | C59: Zero Trust Security Rollout | D59: Configure KPI definitions | E59: E1121 | F59: Saad Alqahtani | G59: D014 | H59: Corporate Training | I59: In Progress | J59: Low | K59: 46152 | L59: 12 | M59: 17 | N59: 39
A60: T0059 | B60: P004 | C60: Zero Trust Security Rollout | D60: Validate user journey | E60: E1066 | F60: Hala Alqahtani | G60: D009 | H60: Sales | I60: In Progress | J60: High | K60: 46252 | L60: 4 | M60: 5 | N60: 45
A61: T0060 | B61: P005 | C61: HR Self-Service Portal | D61: Integrate UAT scenarios | E61: E1111 | F61: Noura Albalawi | G61: D012 | H61: Procurement | I61: In Progress | J61: High | K61: 46199 | L61: 32 | M61: 47 | N61: 49
A62: T0061 | B62: P005 | C62: HR Self-Service Portal | D62: Integrate automation workflow | E62: E1044 | F62: Fatimah Alharthi | G62: D006 | H62: Digital Products | I62: Blocked | J62: High | K62: 46242 | L62: 16 | M62: 22 | N62: 10
A63: T0062 | B63: P005 | C63: HR Self-Service Portal | D63: Migrate user journey | E63: E1056 | F63: Renad Almutairi | G63: D008 | H63: Marketing | I63: In Progress | J63: High | K63: 46161 | L63: 6 | M63: 3 | N63: 39
A64: T0063 | B64: P005 | C64: HR Self-Service Portal | D64: Deploy requirements | E64: E1058 | F64: Omar Alrashid | G64: D008 | H64: Marketing | I64: Not Started | J64: Critical | K64: 46224 | L64: 24 | N64: 93
A65: T0064 | B65: P005 | C65: HR Self-Service Portal | D65: Migrate automation workflow | E65: E1112 | F65: Abdullah Alrashid | G65: D012 | H65: Procurement | I65: Completed | J65: High | K65: 46272 | L65: 4 | M65: 2 | N65: 100
A66: T0065 | B66: P005 | C66: HR Self-Service Portal | D66: Train stakeholder report | E66: E1047 | F66: Saad Alotaibi | G66: D007 | H66: Data & Analytics | I66: Not Started | J66: Low | K66: 46288 | L66: 8 | N66: 86
A67: T0066 | B67: P005 | C67: HR Self-Service Portal | D67: Configure automation workflow | E67: E1101 | F67: Noura Almalki | G67: D011 | H67: Operations | I67: Not Started | J67: Medium | K67: 46123 | L67: 24 | N67: 72
A68: T0067 | B68: P005 | C68: HR Self-Service Portal | D68: Review stakeholder report | E68: E1005 | F68: Yousef Almutairi | G68: D001 | H68: Executive Office | I68: Blocked | J68: High | K68: 46154 | L68: 24 | M68: 23 | N68: 17
A69: T0068 | B69: P006 | C69: Sales CRM Migration | D69: Build UAT scenarios | E69: E1047 | F69: Saad Alotaibi | G69: D007 | H69: Data & Analytics | I69: Blocked | J69: Medium | K69: 46196 | L69: 6 | M69: 3 | N69: 66
A70: T0069 | B70: P006 | C70: Sales CRM Migration | D70: Document access roles | E70: E1050 | F70: Noura Alshehri | G70: D007 | H70: Data & Analytics | I70: In Review | J70: Critical | K70: 46183 | L70: 12 | M70: 19 | N70: 62
A71: T0070 | B71: P006 | C71: Sales CRM Migration | D71: Deploy API endpoints | E71: E1026 | F71: Turki Alsubaie | G71: D004 | H71: Information Technology | I71: Completed | J71: Critical | K71: 46150 | L71: 8 | M71: 11 | N71: 100
A72: T0071 | B72: P006 | C72: Sales CRM Migration | D72: Integrate access roles | E72: E1104 | F72: Nasser Alzahrani | G72: D011 | H72: Operations | I72: In Review | J72: High | K72: 46204 | L72: 16 | M72: 22 | N72: 89
A73: T0072 | B73: P006 | C73: Sales CRM Migration | D73: Validate training guide | E73: E1082 | F73: Renad Alharbi | G73: D010 | H73: Customer Experience | I73: In Progress | J73: Low | K73: 46208 | L73: 12 | M73: 16 | N73: 63
A74: T0073 | B74: P006 | C74: Sales CRM Migration | D74: Test access roles | E74: E1004 | F74: Reem Alrashid | G74: D001 | H74: Executive Office | I74: In Progress | J74: Medium | K74: 46210 | L74: 6 | M74: 3 | N74: 92
A75: T0074 | B75: P006 | C75: Sales CRM Migration | D75: Migrate API endpoints | E75: E1062 | F75: Renad Alzahrani | G75: D009 | H75: Sales | I75: Completed | J75: Low | K75: 46220 | L75: 8 | M75: 12 | N75: 100
A76: T0075 | B76: P006 | C76: Sales CRM Migration | D76: Test release plan | E76: E1058 | F76: Omar Alrashid | G76: D008 | H76: Marketing | I76: Not Started | J76: Medium | K76: 46204 | L76: 8 | N76: 7
A77: T0076 | B77: P006 | C77: Sales CRM Migration | D77: Validate data model | E77: E1107 | F77: Sara Alqahtani | G77: D012 | H77: Procurement | I77: In Progress | J77: Medium | K77: 46155 | L77: 24 | M77: 36 | N77: 66
A78: T0077 | B78: P006 | C78: Sales CRM Migration | D78: Prepare release plan | E78: E1115 | F78: Abdullah Alshammari | G78: D013 | H78: Legal & Compliance | I78: In Progress | J78: High | K78: 46136 | L78: 8 | M78: 9 | N78: 11
A79: T0078 | B79: P006 | C79: Sales CRM Migration | D79: Train database tables | E79: E1065 | F79: Razan Alenezi | G79: D009 | H79: Sales | I79: Not Started | J79: High | K79: 46155 | L79: 4 | N79: 3
A80: T0079 | B80: P006 | C80: Sales CRM Migration | D80: Migrate release plan | E80: E1011 | F80: Turki Alenezi | G80: D002 | H80: Human Resources | I80: Blocked | J80: Critical | K80: 46183 | L80: 4 | M80: 4 | N80: 37
A81: T0080 | B81: P006 | C81: Sales CRM Migration | D81: Integrate requirements | E81: E1083 | F81: Saad Alomari | G81: D010 | H81: Customer Experience | I81: In Progress | J81: Critical | K81: 46239 | L81: 16 | M81: 15 | N81: 20
A82: T0081 | B82: P006 | C82: Sales CRM Migration | D82: Integrate data model | E82: E1057 | F82: Fatimah Alharthi | G82: D008 | H82: Marketing | I82: In Progress | J82: High | K82: 46239 | L82: 8 | M82: 6 | N82: 93
A83: T0082 | B83: P006 | C83: Sales CRM Migration | D83: Configure security controls | E83: E1111 | F83: Noura Albalawi | G83: D012 | H83: Procurement | I83: Not Started | J83: High | K83: 46218 | L83: 6 | N83: 59
A84: T0083 | B84: P006 | C84: Sales CRM Migration | D84: Test database tables | E84: E1016 | F84: Maha Alomari | G84: D003 | H84: Finance | I84: In Progress | J84: Low | K84: 46231 | L84: 4 | M84: 3 | N84: 78
A85: T0084 | B85: P007 | C85: Vendor Risk Dashboard | D85: Deploy release plan | E85: E1032 | F85: Fahad Alfarsi | G85: D005 | H85: Cybersecurity | I85: Completed | J85: High | K85: 46208 | L85: 12 | M85: 16 | N85: 100
A86: T0085 | B86: P007 | C86: Vendor Risk Dashboard | D86: Validate security controls | E86: E1060 | F86: Razan Almutairi | G86: D009 | H86: Sales | I86: In Progress | J86: Low | K86: 46203 | L86: 32 | M86: 33 | N86: 74
A87: T0086 | B87: P007 | C87: Vendor Risk Dashboard | D87: Train API endpoints | E87: E1046 | F87: Salwa Almutairi | G87: D007 | H87: Data & Analytics | I87: In Progress | J87: Critical | K87: 46137 | L87: 16 | M87: 17 | N87: 55
A88: T0087 | B88: P007 | C88: Vendor Risk Dashboard | D88: Prepare release plan | E88: E1018 | F88: Reem Alharbi | G88: D003 | H88: Finance | I88: In Review | J88: High | K88: 46218 | L88: 4 | M88: 3 | N88: 24
A89: T0088 | B89: P007 | C89: Vendor Risk Dashboard | D89: Train stakeholder report | E89: E1047 | F89: Saad Alotaibi | G89: D007 | H89: Data & Analytics | I89: Backlog | J89: Critical | K89: 46198 | L89: 16 | N89: 87
A90: T0089 | B90: P007 | C90: Vendor Risk Dashboard | D90: Configure release plan | E90: E1079 | F90: Noura Almalki | G90: D010 | H90: Customer Experience | I90: Completed | J90: Critical | K90: 46157 | L90: 24 | M90: 32 | N90: 100
A91: T0090 | B91: P007 | C91: Vendor Risk Dashboard | D91: Design requirements | E91: E1121 | F91: Saad Alqahtani | G91: D014 | H91: Corporate Training | I91: Not Started | J91: Critical | K91: 46161 | L91: 4 | N91: 17
A92: T0091 | B92: P007 | C92: Vendor Risk Dashboard | D92: Prepare data model | E92: E1092 | F92: Sara Alharbi | G92: D011 | H92: Operations | I92: In Progress | J92: Medium | K92: 46246 | L92: 8 | M92: 6 | N92: 20
A93: T0092 | B93: P007 | C93: Vendor Risk Dashboard | D93: Design data model | E93: E1051 | F93: Mohammed Aljohani | G93: D007 | H93: Data & Analytics | I93: In Progress | J93: Critical | K93: 46211 | L93: 16 | M93: 16 | N93: 42
A94: T0093 | B94: P007 | C94: Vendor Risk Dashboard | D94: Migrate training guide | E94: E1087 | F94: Razan Almutairi | G94: D010 | H94: Customer Experience | I94: In Progress | J94: Low | K94: 46231 | L94: 40 | M94: 31 | N94: 99
A95: T0094 | B95: P007 | C95: Vendor Risk Dashboard | D95: Migrate security controls | E95: E1075 | F95: Turki Alrashid | G95: D010 | H95: Customer Experience | I95: In Progress | J95: Medium | K95: 46138 | L95: 32 | M95: 21 | N95: 4
A96: T0095 | B96: P007 | C96: Vendor Risk Dashboard | D96: Build automation workflow | E96: E1074 | F96: Fatimah Alrashid | G96: D009 | H96: Sales | I96: Backlog | J96: High | K96: 46173 | L96: 32 | N96: 88
A97: T0096 | B97: P007 | C97: Vendor Risk Dashboard | D97: Analyze security controls | E97: E1027 | F97: Mohammed Alenezi | G97: D004 | H97: Information Technology | I97: In Review | J97: Critical | K97: 46253 | L97: 4 | M97: 5 | N97: 71
A98: T0097 | B98: P007 | C98: Vendor Risk Dashboard | D98: Configure release plan | E98: E1042 | F98: Abdullah Alharthi | G98: D006 | H98: Digital Products | I98: In Progress | J98: Medium | K98: 46259 | L98: 40 | M98: 60 | N98: 45
A99: T0098 | B99: P008 | C99: AI Support Assistant | D99: Validate user journey | E99: E1099 | F99: Raghad Alamri | G99: D011 | H99: Operations | I99: In Review | J99: High | K99: 46217 | L99: 40 | M99: 28 | N99: 71
A100: T0099 | B100: P008 | C100: AI Support Assistant | D100: Configure release plan | E100: E1039 | F100: Mohammed Alghamdi | G100: D006 | H100: Digital Products | I100: In Review | J100: Medium | K100: 46129 | L100: 40 | M100: 33 | N100: 92
...

Sheet Meetings
A1: Meeting ID | B1: Project ID | C1: Project | D1: Meeting Type | E1: Date/Time | F1: Duration Minutes | G1: Organizer ID | H1: Organizer | I1: Attendees Count | J1: Outcome | K1: Location/Channel
A2: M0001 | B2: P016 | C2: Customer Feedback 360 | D2: Design Workshop | E2: 46155.667 | F2: 45 | G2: E1010 | H2: Khalid Almalki | I2: 19 | J2: Action items assigned | K2: Hybrid
A3: M0002 | B3: P002 | C3: Customer Mobile App Revamp | D3: Risk Review | E3: 46158.417 | F3: 120 | G3: E1083 | H3: Saad Alomari | I3: 16 | J3: Action items assigned | K3: Teams
A4: M0003 | B4: P015 | C4: Learning Experience Platform | D4: Executive Update | E4: 46142.667 | F4: 120 | G4: E1058 | H4: Omar Alrashid | I4: 6 | J4: Information shared | K4: Hybrid
A5: M0004 | B5: P004 | C5: Zero Trust Security Rollout | D5: Retrospective | E5: 46156.625 | F5: 30 | G5: E1014 | H5: Razan Alomari | I5: 16 | J5: Action items assigned | K5: Teams
A6: M0005 | B6: P003 | C6: ERP Finance Automation | D6: Executive Update | E6: 46183.583 | F6: 60 | G6: E1114 | H6: Reem Alghamdi | I6: 20 | J6: Action items assigned | K6: Hybrid
A7: M0006 | B7: P012 | C7: Operations Control Tower | D7: Training Session | E7: 46042.667 | F7: 45 | G7: E1109 | H7: Razan Albalawi | I7: 18 | J7: Action items assigned | K7: Client Site
A8: M0007 | B8: P023 | C8: Revenue Forecasting Engine | D8: Risk Review | E8: 46197.458 | F8: 90 | G8: E1015 | H8: Mohammed Alzahrani | I8: 7 | J8: Follow-up required | K8: Teams
A9: M0008 | B9: P011 | C9: Executive KPI Cockpit | D9: Sprint Planning | E9: 46119.667 | F9: 60 | G9: E1071 | H9: Mona Alsubaie | I9: 20 | J9: Action items assigned | K9: Teams
A10: M0009 | B10: P006 | C10: Sales CRM Migration | D10: Risk Review | E10: 46155.417 | F10: 90 | G10: E1014 | H10: Razan Alomari | I10: 12 | J10: Follow-up required | K10: Teams
A11: M0010 | B11: P013 | C11: Procurement e-Sourcing | D11: UAT Session | E11: 46084.542 | F11: 45 | G11: E1092 | H11: Sara Alharbi | I11: 14 | J11: Decision made | K11: Teams
A12: M0011 | B12: P021 | C12: Internal Knowledge Base | D12: Training Session | E12: 46201.583 | F12: 30 | G12: E1099 | H12: Raghad Alamri | I12: 18 | J12: Action items assigned | K12: Board Room
A13: M0012 | B13: P016 | C13: Customer Feedback 360 | D13: Executive Update | E13: 46030.583 | F13: 30 | G13: E1071 | H13: Mona Alsubaie | I13: 17 | J13: Information shared | K13: Board Room
... A181: M0180 | B181: P020 | C181: Field Service Mobile Toolkit | D181: Retrospective | E181: 46065.625 | F181: 30 | G181: E1049 | H181: Omar Alghamdi | I181: 22 | J181: Information shared | K181: Teams

Sheet Weekly Updates
A1: Update ID | B1: Week Starting | C1: Project ID | D1: Project | E1: Department | F1: Health | G1: Status | H1: Progress % | I1: Key Accomplishment | J1: Blocker/Risk | K1: Next Step
A2: WU0001 | B2: 46027 | C2: P006 | D2: Sales CRM Migration | E2: Sales | F2: Amber | G2: In Progress | H2: 13 | I2: Completed milestone | J2: Need SME approval | K2: Add support resource
A3: WU0002 | B3: 46027 | C3: P002 | D3: Customer Mobile App Revamp | E3: Sales | F3: Green | G3: At Risk | H3: 90 | I3: Completed milestone | J3: Need SME approval | K3: Add support resource
A4: WU0003 | B4: 46027 | C4: P010 | D4: Cloud Cost Optimization | E4: Executive Office | F4: Green | G4: At Risk | H4: 23 | I4: Dependency raised | J4: Data access pending | K4: Add support resource
A5: WU0004 | B5: 46027 | C5: P007 | D5: Vendor Risk Dashboard | E5: Digital Products | F5: Amber | G5: Completed | H5: 5 | I5: Dependency raised | J5: Data access pending | K5: Re-baseline timeline
A6: WU0005 | B6: 46027 | C6: P020 | D6: Field Service Mobile Toolkit | E6: Sales | F6: Green | G6: Planning | H6: 20 | I6: Completed milestone | J6: Need SME approval | K6: Re-baseline timeline
A7: WU0006 | B7: 46027 | C7: P009 | D7: Digital Onboarding Journey | E7: Legal & Compliance | F7: Green | G7: At Risk | H7: 64 | I7: Scope clarified | J7: No major blockers | K7: Re-baseline timeline
A8: WU0007 | B8: 46027 | C8: P023 | D8: Revenue Forecasting Engine | E8: Corporate Training | F8: Amber | G8: In Progress | H8: 3 | I8: Stakeholder feedback received | J8: Need SME approval | K8: Escalate decision
A9: WU0008 | B9: 46027 | C9: P015 | D9: Learning Experience Platform | E9: Executive Office | F9: Amber | G9: At Risk | H9: 11 | I9: Budget reviewed | J9: Resource capacity issue | K9: Schedule workshop
A10: WU0009 | B10: 46027 | C10: P001 | D10: Enterprise Data Platform | E10: Executive Office | F10: Amber | G10: In Progress | H10: 80 | I10: Budget reviewed | J10: Waiting for vendor | K10: Add support resource
A11: WU0010 | B11: 46027 | C11: P018 | D11: Identity Access Review | E11: Marketing | F11: Green | G11: Planning | H11: 39 | I11: Stakeholder feedback received | J11: Need SME approval | K11: Add support resource
A12: WU0011 | B12: 46027 | C12: P021 | D12: Internal Knowledge Base | E12: Marketing | F12: Green | G12: Completed | H12: 17 | I12: Stakeholder feedback received | J12: Data access pending | K12: Escalate decision
A13: WU0012 | B13: 46027 | C13: P011 | D13: Executive KPI Cockpit | E13: Finance | F13: Green | G13: Not Started | H13: 90 | I13: Stakeholder feedback received | J13: Waiting for vendor | K13: Add support resource
... A368: WU0367 | B368: 46202 | C368: P021 | D368: Internal Knowledge Base | E368: Marketing | F368: Green | G368: Completed | H368: 25 | I368: Dependency raised | J368: Data access pending | K368: Add support resource

Sheet Activity Log
A1: Activity ID | B1: Timestamp | C1: Employee ID | D1: Employee | E1: Department ID | F1: Department | G1: Project ID | H1: Project | I1: Task ID | J1: Activity Type | K1: Impact | L1: Source
A2: A00001 | B2: 46100.427 | C2: E1013 | D2: Saad Alshehri | E2: D003 | F2: Finance | G2: P014 | H2: Compliance Case Management | I2: T0203 | J2: Approved milestone | K2: Low | L2: Web App
A3: A00002 | B3: 46196.382 | C3: E1046 | D3: Salwa Almutairi | E3: D007 | F3: Data & Analytics | G3: P009 | H3: Digital Onboarding Journey | I3: T0127 | J3: Completed UAT | K3: High | L3: Web App
A4: A00003 | B4: 46133.344 | C4: E1104 | D4: Nasser Alzahrani | E4: D011 | F4: Operations | G4: P003 | H4: ERP Finance Automation | I4: T0035 | J4: Updated status | K4: High | L4: Mobile App
A5: A00004 | B5: 46113.792 | C5: E1063 | D5: Nasser Almalki | E5: D009 | F5: Sales | G5: P009 | H5: Digital Onboarding Journey | I5: T0126 | J5: Published dashboard | K5: High | L5: Email
A6: A00005 | B6: 46203.33 | C6: E1115 | D6: Abdullah Alshammari | E6: D013 | F6: Legal & Compliance | G6: P005 | H6: HR Self-Service Portal | I6: T0061 | J6: Published dashboard | K6: Medium | L6: Web App
A7: A00006 | B7: 46049.625 | C7: E1014 | D7: Razan Alomari | E7: D003 | F7: Finance | G7: P020 | H7: Field Service Mobile Toolkit | I7: T0274 | J7: Approved milestone | K7: Low | L7: Mobile App
A8: A00007 | B8: 46115.389 | C8: E1081 | D8: Khalid Alfarsi | E8: D010 | F8: Customer Experience | G8: P004 | H8: Zero Trust Security Rollout | I8: T0048 | J8: Updated budget | K8: Medium | L8: System Job
A9: A00008 | B9: 46062.729 | C9: E1064 | D9: Khalid Albalawi | E9: D009 | F9: Sales | G9: P024 | H9: Employee Engagement Analytics | I9: T0324 | J9: Assigned owner | K9: Low | L9: Web App
A10: A00009 | B10: 46129.792 | C10: E1109 | D10: Razan Albalawi | E10: D012 | F10: Procurement | G10: P007 | H10: Vendor Risk Dashboard | I10: T0091 | J10: Commented on risk | K10: Medium | L10: Email
A11: A00010 | B11: 46044.479 | C11: E1037 | D11: Abeer Alqahtani | E11: D006 | F11: Digital Products | G11: P017 | H11: Warehouse Scheduling System | I11: T0235 | J11: Updated budget | K11: Medium | L11: Email
A12: A00011 | B12: 46061.823 | C12: E1081 | D12: Khalid Alfarsi | E12: D010 | F12: Customer Experience | G12: P022 | H12: Incident Response Automation | I12: T0293 | J12: Published dashboard | K12: Low | L12: Mobile App
A13: A00012 | B13: 46127.604 | C13: E1103 | D13: Abdullah Almutairi | E13: D011 | F13: Operations | G13: P014 | H13: Compliance Case Management | I13: T0201 | J13: Created task | K13: Medium | L13: Mobile App
... A701: A00700 | B701: 46141.753 | C701: E1112 | D701: Abdullah Alrashid | E701: D012 | F701: Procurement | G701: P006 | H701: Sales CRM Migration | I701: T0075 | J701: Created task | K701: High | L701: Web App

Sheet Lists
A1: Statuses | B1: Priorities | C1: Risk Levels | D1: Health | E1: Meeting Types
A2: Not Started | B2: Low | C2: Low | D2: Green | E2: Steering Committee
A3: Planning | B3: Medium | C3: Medium | D3: Amber | E3: Sprint Planning
A4: In Progress | B4: High | C4: High | D4: Red | E4: Daily Standup
A5: At Risk | B5: Critical | E5: Risk Review
A6: On Hold | E6: Vendor Review
A7: Completed | E7: Design Workshop
